tree.py
scenario_tree-0.2.dist-info/METADATA
scenario_tree-0.2.dist-info/WHEEL
scenario_tree-0.2.dist-info/top_level.txt
scenario_tree-0.2.dist-info/RECORD
