Metadata-Version: 2.1
Name: scenario-tree
Version: 0.2
Summary: Get the sceanrio tree stucture
Author: Zhen Chen
Author-email: 15011074486@163.com
